wagtail_constance-0.0.2.dist-info/DESCRIPTION.rst
wagtail_constance-0.0.2.dist-info/METADATA
wagtail_constance-0.0.2.dist-info/RECORD
wagtail_constance-0.0.2.dist-info/WHEEL
wagtail_constance-0.0.2.dist-info/metadata.json
wagtail_constance-0.0.2.dist-info/top_level.txt
wagtailconstance/__init__.py
wagtailconstance/views.py
wagtailconstance/wagtail_hooks.py
wagtailconstance/templates/wagtailconstance/config.html
