Metadata-Version: 2.0
Name: wagtail-constance
Version: 0.0.2
Summary: django-constance integration for Wagtail CMS
Home-page: http://github.com/MechanisM/wagtail-constance
Author: Eugene MechanisM
Author-email: eugene@mechanism.pro
License: MIT
Keywords: django,config,constance
Platform: UNKNOWN
Classifier: Intended Audience :: Developers
Classifier: License :: OSI Approved :: MIT License
Classifier: Programming Language :: Python :: 3.4
